helloworld/__init__.py
helloworld/hello.py
helloworld_shruti_package-0.1.2.dist-info/METADATA
helloworld_shruti_package-0.1.2.dist-info/WHEEL
helloworld_shruti_package-0.1.2.dist-info/top_level.txt
helloworld_shruti_package-0.1.2.dist-info/RECORD
