Metadata-Version: 2.2
Name: helloworld_shruti_package
Version: 0.1.2
Summary: A package to print Hello World
Author: Your Name
Author-email: your.email@example.com
Dynamic: author
Dynamic: author-email
Dynamic: summary
